odoo/addons/sale_automatic_workflow_delivery_state/README.rst
odoo/addons/sale_automatic_workflow_delivery_state/__init__.py
odoo/addons/sale_automatic_workflow_delivery_state/__manifest__.py
odoo/addons/sale_automatic_workflow_delivery_state/i18n/it.po
odoo/addons/sale_automatic_workflow_delivery_state/i18n/sale_automatic_workflow_delivery_state.pot
odoo/addons/sale_automatic_workflow_delivery_state/models/sale_order.py
odoo/addons/sale_automatic_workflow_delivery_state/readme/DESCRIPTION.rst
odoo/addons/sale_automatic_workflow_delivery_state/readme/ROADMAP.rst
odoo/addons/sale_automatic_workflow_delivery_state/static/description/icon.png
odoo/addons/sale_automatic_workflow_delivery_state/static/description/index.html
odoo14_addon_sale_automatic_workflow_delivery_state-14.0.1.0.1.dev7.dist-info/METADATA
odoo14_addon_sale_automatic_workflow_delivery_state-14.0.1.0.1.dev7.dist-info/WHEEL
odoo14_addon_sale_automatic_workflow_delivery_state-14.0.1.0.1.dev7.dist-info/top_level.txt
odoo14_addon_sale_automatic_workflow_delivery_state-14.0.1.0.1.dev7.dist-info/RECORD
